dummy.py
python_dummy-0.1.0.dist-info/LICENSE
python_dummy-0.1.0.dist-info/METADATA
python_dummy-0.1.0.dist-info/WHEEL
python_dummy-0.1.0.dist-info/entry_points.txt
python_dummy-0.1.0.dist-info/top_level.txt
python_dummy-0.1.0.dist-info/RECORD
