Metadata-Version: 2.1
Name: python-dummy
Version: 0.1.0
Summary: Dummy package generator.
Home-page: https://github.com/JarryShaw/pypi
Author: Jarry Shaw
Author-email: jarryshaw@icloud.com
Maintainer: Jarry Shaw
Maintainer-email: jarryshaw@icloud.com
License: MIT License
Download-URL: https://github.com/JarryShaw/pypi/archive/v0.1.0.tar.gz
Keywords: dummy
Platform: any
Classifier: Development Status :: 5 - Production/Stable
Classifier: Intended Audience :: Developers
Classifier: License :: OSI Approved :: MIT License
Classifier: Natural Language :: English
Classifier: Operating System :: OS Independent
Classifier: Programming Language :: Python
Classifier: Topic :: Software Development
Classifier: Topic :: Utilities
Requires-Dist: PyYAML
Requires-Dist: simplejson
